{
    "fluentMethods": true,
    "relationships": [
        {
            "relationshipType": "many-to-one",
            "relationshipName": "companyResource",
            "otherEntityName": "companyResource",
            "otherEntityField": "id"
        }
    ],
    "fields": [
        {
            "fieldName": "name",
            "fieldType": "String",
            "fieldValidateRules": [
                "required"
            ]
        },
        {
            "fieldName": "value",
            "fieldType": "BigDecimal",
            "fieldValidateRules": [
                "required"
            ]
        }
    ],
    "changelogDate": "20170205202809",
    "entityTableName": "menu",
    "dto": "no",
    "pagination": "pager",
    "service": "serviceClass"
}
